pyrieef/__init__.py
pyrieef/setup.py
pyrieef/geometry/__init__.py
pyrieef/geometry/attractors.py
pyrieef/geometry/charge_simulation.py
pyrieef/geometry/diffeomorphisms.py
pyrieef/geometry/differentiable_geometry.py
pyrieef/geometry/geodesics.py
pyrieef/geometry/pixel_map.py
pyrieef/geometry/utils.py
pyrieef/geometry/workspace.py
pyrieef/graph/__init__.py
pyrieef/graph/shortest_path.py
pyrieef/learning/__init__.py
pyrieef/learning/common_imports.py
pyrieef/learning/dataset.py
pyrieef/learning/demonstrations.py
pyrieef/learning/inverse_optimal_control.py
pyrieef/learning/networks.py
pyrieef/learning/one_demo.py
pyrieef/learning/random_environment.py
pyrieef/learning/random_paths.py
pyrieef/learning/tf_autoencoder.py
pyrieef/learning/tf_autoencoder_2.py
pyrieef/learning/tf_costpredict.py
pyrieef/learning/tf_costpredict_2.py
pyrieef/learning/tf_costpredict_3.py
pyrieef/learning/tf_costpredict_4.py
pyrieef/learning/tf_networks.py
pyrieef/learning/train_supervised_cost_net.py
pyrieef/learning/visualize_data.py
pyrieef/motion/__init__.py
pyrieef/motion/control.py
pyrieef/motion/cost_terms.py
pyrieef/motion/ilqr.py
pyrieef/motion/objective.py
pyrieef/motion/trajectory.py
pyrieef/optimization/__init__.py
pyrieef/optimization/algorithms.py
pyrieef/optimization/common_imports.py
pyrieef/optimization/optimization.py
pyrieef/rendering/__init__.py
pyrieef/rendering/common_imports.py
pyrieef/rendering/heightmap.py
pyrieef/rendering/heightmap_renderer.py
pyrieef/rendering/optimization.py
pyrieef/rendering/plannar_gl.py
pyrieef/rendering/shader.py
pyrieef/rendering/show_image.py
pyrieef/rendering/sphere.py
pyrieef/rendering/workspace_renderer.py
pyrieef/utils/__init__.py
pyrieef/utils/collision_checking.py
pyrieef/utils/common_imports.py
pyrieef/utils/misc.py
pyrieef/utils/options.py
pyrieef/utils/timer.py
pyrieef-0.0.1.dist-info/METADATA
pyrieef-0.0.1.dist-info/RECORD
pyrieef-0.0.1.dist-info/WHEEL
pyrieef-0.0.1.dist-info/top_level.txt
tests/__init__.py
tests/test_attractors.py
tests/test_diffeomorphisms.py
tests/test_differentiable_geometry.py
