Metadata-Version: 2.1
Name: pyrieef
Version: 0.0.1
Summary: Motion planning and control python package
Home-page: https://github.com/jmainpri/pyrieef
Author: Jim Mainprice
Author-email: mainprice@gmail.com
License: UNKNOWN
Platform: UNKNOWN
Classifier: Programming Language :: Python :: 2
Classifier: License :: OSI Approved :: MIT License
Classifier: Operating System :: OS Independent
